cryptocurrency_wallet_generator/__init__.py
cryptocurrency_wallet_generator/currencies/__init__.py
cryptocurrency_wallet_generator/currencies/bitcoin/__init__.py
cryptocurrency_wallet_generator/currencies/bitcoin/base58.py
cryptocurrency_wallet_generator/currencies/bitcoincash/__init__.py
cryptocurrency_wallet_generator/currencies/dash/__init__.py
cryptocurrency_wallet_generator/currencies/ethereum/__init__.py
cryptocurrency_wallet_generator/currencies/litecoin/__init__.py
InstantlyEscrow-0.0.7.dist-info/METADATA
InstantlyEscrow-0.0.7.dist-info/WHEEL
InstantlyEscrow-0.0.7.dist-info/dependency_links.txt
InstantlyEscrow-0.0.7.dist-info/top_level.txt
InstantlyEscrow-0.0.7.dist-info/RECORD
