Metadata-Version: 2.1
Name: InstantlyEscrow
Version: 0.0.7
Summary: Simple Python package that can generate wallets for several cryptocurrencies
Home-page: https://github.com/clockwrks/Instantly-Escrow-Crypto
Author: aruseni
Author-email: aruseni.magiku@gmail.com
License: Creative Commons Attribution-Noncommercial-Share Alike license
Platform: any
Requires-Dist: ecdsa (==0.13)
